lut_2b_multiplier/test.v
module test
(
    input[63:0] result_2b,

    output reg resetn_2b,
    output reg clk_2b,
    output reg[31:0] source_number_2b_0,
    output reg[1:0] source_number_2b_1
);

initial begin
    $dumpfile("lut_multiplier_2b.vcd");
	$dumpvars;

    @(posedge clk_2b);
	@(posedge clk_2b);
    @(posedge clk_2b);
        source_number_2b_0 <= 852147;
    @(posedge clk_2b);
        source_number_2b_1 <= 0;
	@(posedge clk_2b);
        //source_number_2b_0 = 4;
        source_number_2b_1 <= 1;
	@(posedge clk_2b); 
        //source_number_2b_0 = 4;
        source_number_2b_1 <= 2;
	@(posedge clk_2b); 
        //source_number_2b_0 = 4;
        source_number_2b_1 <= 3;
    @(posedge clk_2b);@(posedge clk_2b);@(posedge clk_2b);@(posedge clk_2b);@(posedge clk_2b);@(posedge clk_2b);
        source_number_2b_1 <= 3;
    $finish;
end

//clk_2b.
initial clk_2b <= 0;
always	#2 clk_2b <= ~clk_2b;

//resetn.
initial
begin
	#0
	resetn_2b = 1'b1;
	@(posedge clk_2b);
	resetn_2b = 1'b1;
	@(posedge clk_2b);
	resetn_2b = 1'b0;
end

endmodule

lut_4b_multiplier/lut_multiplier_2b_cond.v
module lut_multiplier_2b_cond
(
    input resetn_2b,
    input clk_2b,
    input[31:0] source_number_2b_0,
    input[1:0] source_number_2b_1,

    output reg[63:0] result_2b
);

always@(posedge clk_2b) begin
    if(resetn_2b == 1) begin
        result_2b <= 0;
    end
    else begin
        if(source_number_2b_1 == 0) begin
            result_2b <= 0;
        end
        else if (source_number_2b_1 == 1) begin
            result_2b <= source_number_2b_0;
        end
        else if (source_number_2b_1 == 2) begin
            result_2b <= source_number_2b_0 << 1;           //Desplazamiento metiendo cero.
        end
        else if (source_number_2b_1 == 3) begin
            result_2b <= (source_number_2b_0 << 1) + source_number_2b_0;     //Desplazamiento metiendo cero.
        end
        else begin
            result_2b <= 0;
        end
    end
end

endmodule

lut_2b_multiplier/test_bench.v
`timescale 1ns/100ps

`include "lut_multiplier_2b_cond.v"
`include "test.v"

module test_bench;

wire resetn_2b, clk_2b;
wire[31:0] source_number_2b_0;
wire[1:0] source_number_2b_1;
wire[63:0] result_2b; 

lut_multiplier_2b_cond COND(
    /*AUTOINST*/
			    // Outputs
			    .result_2b		(result_2b[63:0]),
			    // Inputs
			    .resetn_2b		(resetn_2b),
			    .clk_2b		(clk_2b),
			    .source_number_2b_0	(source_number_2b_0[31:0]),
			    .source_number_2b_1	(source_number_2b_1[1:0]));

test TEST(
    /*AUTOINST*/
	  // Outputs
	  .resetn_2b			(resetn_2b),
	  .clk_2b			(clk_2b),
	  .source_number_2b_0		(source_number_2b_0[31:0]),
	  .source_number_2b_1		(source_number_2b_1[1:0]),
	  // Inputs
	  .result_2b			(result_2b[63:0]));
endmodule

lut_2b_multiplier/lut_multiplier_2b.vcd
$date
	Sun May  2 23:35:22 2021
$end
$version
	Icarus Verilog
$end
$timescale
	100ps
$end
$scope module test_bench $end
$var wire 2 ! source_number_2b_1 [1:0] $end
$var wire 32 " source_number_2b_0 [31:0] $end
$var wire 64 # result_2b [63:0] $end
$var wire 1 $ resetn_2b $end
$var wire 1 % clk_2b $end
$scope module COND $end
$var wire 2 & source_number_2b_1 [1:0] $end
$var wire 32 ' source_number_2b_0 [31:0] $end
$var wire 1 $ resetn_2b $end
$var wire 1 % clk_2b $end
$var reg 64 ( result_2b [63:0] $end
$upscope $end
$scope module TEST $end
$var wire 64 ) result_2b [63:0] $end
$var reg 1 % clk_2b $end
$var reg 1 $ resetn_2b $end
$var reg 32 * source_number_2b_0 [31:0] $end
$var reg 2 + source_number_2b_1 [1:0] $end
$upscope $end
$upscope $end
$enddefinitions $end
#0
$dumpvars
bx +
bx *
bx )
bx (
bx '
bx &
0%
1$
bx #
bx "
bx !
$end
#20
b0 #
b0 (
b0 )
1%
#40
0%
#60
0$
1%
#80
0%
#100
b11010000000010110011 "
b11010000000010110011 '
b11010000000010110011 *
1%
#120
0%
#140
b0 !
b0 &
b0 +
1%
#160
0%
#180
b1 !
b1 &
b1 +
1%
#200
0%
#220
b10 !
b10 &
b10 +
b11010000000010110011 #
b11010000000010110011 (
b11010000000010110011 )
1%
#240
0%
#260
b110100000000101100110 #
b110100000000101100110 (
b110100000000101100110 )
b11 !
b11 &
b11 +
1%
#280
0%
#300
b1001110000001000011001 #
b1001110000001000011001 (
b1001110000001000011001 )
1%
