lut_4b_multiplier/test.v
module test
(
    output reg resetn_4b,
    output reg clk_4b,
    output reg[31:0] source_number_4b_0,
    output reg[3:0] source_number_4b_1,

    input[63:0] result_4b
);

initial begin
    $dumpfile("lut_multiplier_4b.vcd");
	$dumpvars;

    @(posedge clk_4b);
	@(posedge clk_4b);
    @(posedge clk_4b);
        source_number_4b_0 <= 85442222;
    @(posedge clk_4b);
        source_number_4b_1 <= 0;
	@(posedge clk_4b);
        source_number_4b_1 <= 3;
	@(posedge clk_4b); 
        source_number_4b_1 <= 8;
	@(posedge clk_4b); 
        source_number_4b_1 <= 2;
    @(posedge clk_4b);@(posedge clk_4b);@(posedge clk_4b);@(posedge clk_4b);@(posedge clk_4b);@(posedge clk_4b);
        source_number_4b_1 <= 3;
    $finish;
end

//clk_4b.
initial clk_4b <= 0;
always	#2 clk_4b <= ~clk_4b;

//resetn.
initial
begin
	#0
	resetn_4b = 1'b1;
	@(posedge clk_4b);
	resetn_4b = 1'b1;
	@(posedge clk_4b);
	resetn_4b = 1'b0;
end

endmodule

lut_4b_multiplier/lut_multiplier_2b_cond.v
module lut_multiplier_2b_cond
(
    input resetn_2b,
    input clk_2b,
    input[31:0] source_number_2b_0,
    input[1:0] source_number_2b_1,

    output reg[63:0] result_2b
);

always@(posedge clk_2b) begin
    if(resetn_2b == 1) begin
        result_2b <= 0;
    end
    else begin
        if(source_number_2b_1 == 0) begin
            result_2b <= 0;
        end
        else if (source_number_2b_1 == 1) begin
            result_2b <= source_number_2b_0;
        end
        else if (source_number_2b_1 == 2) begin
            result_2b <= source_number_2b_0 << 1;           //Desplazamiento metiendo cero.
        end
        else if (source_number_2b_1 == 3) begin
            result_2b <= (source_number_2b_0 << 1) + source_number_2b_0;     //Desplazamiento metiendo cero.
        end
        else begin
            result_2b <= 0;
        end
    end
end

endmodule

lut_32b_multiplier/lut_multiplier_4b_cond.v
`include "lut_multiplier_2b_cond.v"

module lut_multiplier_4b_cond
(
    input resetn_4b,
    input clk_4b,
    input[31:0] source_number_4b_0,
    input[3:0] source_number_4b_1,

    output reg[63:0] result_4b
);

wire[31:0] result_4b_0, result_4b_1;

always @ (*) begin
    if(resetn_4b == 1) begin
        result_4b = 0;
    end
    else begin
        result_4b = result_4b_0 + 4*result_4b_1;
    end
end

//lut_multiplier_2b instances.

lut_multiplier_2b_cond lut_2B_0(
    .resetn_2b              (resetn_4b),
    .clk_2b                 (clk_4b),
    .source_number_2b_0     (source_number_4b_0),
    .source_number_2b_1     (source_number_4b_1[1:0]),
    .result_2b              (result_4b_0)
);

lut_multiplier_2b_cond lut_2B_1(
    .resetn_2b              (resetn_4b),
    .clk_2b                 (clk_4b),
    .source_number_2b_0     (source_number_4b_0),
    .source_number_2b_1     (source_number_4b_1[3:2]),
    .result_2b              (result_4b_1)
);

endmodule

lut_4b_multiplier/test_bench.v
`timescale 1ns/100ps

`include "lut_multiplier_4b_cond.v"
`include "test.v"

module test_bench;

wire resetn_4b, clk_4b;
wire[31:0] source_number_4b_0;
wire[3:0] source_number_4b_1;
wire[63:0] result_4b; 

lut_multiplier_4b_cond COND(
    /*AUTOINST*/
			    // Outputs
			    .result_4b		(result_4b[63:0]),
			    // Inputs
			    .resetn_4b		(resetn_4b),
			    .clk_4b		(clk_4b),
			    .source_number_4b_0	(source_number_4b_0[31:0]),
			    .source_number_4b_1	(source_number_4b_1[3:0]));

test TEST(
    /*AUTOINST*/
	  // Outputs
	  .resetn_4b			(resetn_4b),
	  .clk_4b			(clk_4b),
	  .source_number_4b_0		(source_number_4b_0[31:0]),
	  .source_number_4b_1		(source_number_4b_1[3:0]),
	  // Inputs
	  .result_4b			(result_4b[63:0]));
endmodule

lut_4b_multiplier/lut_multiplier_4b.vcd
$date
	Sun May  2 23:40:10 2021
$end
$version
	Icarus Verilog
$end
$timescale
	100ps
$end
$scope module test_bench $end
$var wire 4 ! source_number_4b_1 [3:0] $end
$var wire 32 " source_number_4b_0 [31:0] $end
$var wire 64 # result_4b [63:0] $end
$var wire 1 $ resetn_4b $end
$var wire 1 % clk_4b $end
$scope module COND $end
$var wire 4 & source_number_4b_1 [3:0] $end
$var wire 32 ' source_number_4b_0 [31:0] $end
$var wire 32 ( result_4b_1 [31:0] $end
$var wire 32 ) result_4b_0 [31:0] $end
$var wire 1 $ resetn_4b $end
$var wire 1 % clk_4b $end
$var reg 64 * result_4b [63:0] $end
$scope module lut_2B_0 $end
$var wire 2 + source_number_2b_1 [1:0] $end
$var wire 32 , source_number_2b_0 [31:0] $end
$var wire 1 $ resetn_2b $end
$var wire 1 % clk_2b $end
$var reg 64 - result_2b [63:0] $end
$upscope $end
$scope module lut_2B_1 $end
$var wire 2 . source_number_2b_1 [1:0] $end
$var wire 32 / source_number_2b_0 [31:0] $end
$var wire 1 $ resetn_2b $end
$var wire 1 % clk_2b $end
$var reg 64 0 result_2b [63:0] $end
$upscope $end
$upscope $end
$scope module TEST $end
$var wire 64 1 result_4b [63:0] $end
$var reg 1 % clk_4b $end
$var reg 1 $ resetn_4b $end
$var reg 32 2 source_number_4b_0 [31:0] $end
$var reg 4 3 source_number_4b_1 [3:0] $end
$upscope $end
$upscope $end
$enddefinitions $end
#0
$dumpvars
bx 3
bx 2
b0 1
bx 0
bx /
bx .
bx -
bx ,
bx +
b0 *
bx )
bx (
bx '
bx &
0%
1$
b0 #
bx "
bx !
$end
#20
b0 )
b0 (
b0 -
b0 0
1%
#40
0%
#60
0$
1%
#80
0%
#100
b101000101111011111010101110 "
b101000101111011111010101110 '
b101000101111011111010101110 ,
b101000101111011111010101110 /
b101000101111011111010101110 2
1%
#120
0%
#140
b0 .
b0 +
b0 !
b0 &
b0 3
1%
#160
0%
#180
b11 +
b11 !
b11 &
b11 3
1%
#200
0%
#220
b1111010001110011110000001010 #
b1111010001110011110000001010 *
b1111010001110011110000001010 1
b10 .
b0 +
b1111010001110011110000001010 )
b1000 !
b1000 &
b1000 3
b1111010001110011110000001010 -
1%
#240
0%
#260
b101000101111011111010101110000 #
b101000101111011111010101110000 *
b101000101111011111010101110000 1
b0 )
b1010001011110111110101011100 (
b0 .
b10 +
b0 -
b1010001011110111110101011100 0
b10 !
b10 &
b10 3
1%
#280
0%
#300
b1010001011110111110101011100 #
b1010001011110111110101011100 *
b1010001011110111110101011100 1
b0 (
b1010001011110111110101011100 )
b0 0
b1010001011110111110101011100 -
1%
#320
0%
#340
1%
#360
0%
#380
1%
#400
0%
#420
1%
#440
0%
#460
1%
#480
0%
#500
b11 +
b11 !
b11 &
b11 3
1%
