lut_32b_multiplier/test.v
module test
(
    output reg resetn_32b,
    output reg clk_32b,
    output reg[31:0] source_number_32b_0,
    output reg[31:0] source_number_32b_1,

    input[63:0] result_64b
); 

initial begin
    $dumpfile("lut_multiplier_32b.vcd");
	$dumpvars;

    @(posedge clk_32b);
	@(posedge clk_32b);
    @(posedge clk_32b);
        source_number_32b_0 <= 120;
        source_number_32b_1 <= 2;
    repeat(2) @(posedge clk_32b);
        source_number_32b_0 <= 19;
        source_number_32b_1 <= 17;
    repeat(2) @(posedge clk_32b);
        source_number_32b_0 <= 3628800;
        source_number_32b_1 <= 11;
    repeat(2) @(posedge clk_32b);
        source_number_32b_0 <= 39916800;
        source_number_32b_1 <= 12;
    repeat(2) @(posedge clk_32b);
        source_number_32b_0 <= 39916800;
        source_number_32b_1 <= 3628800;
    repeat(27) @(posedge clk_32b);
        source_number_32b_0 <= 39916800;

    $finish;
end

//clk_32b.
initial clk_32b <= 0;
always	#2 clk_32b <= ~clk_32b;

//resetn.
initial
begin
	#0
	resetn_32b = 1'b1;
	@(posedge clk_32b);
	resetn_32b = 1'b1;
	@(posedge clk_32b);
	resetn_32b = 1'b0;
end

endmodule

lut_4b_multiplier/lut_multiplier_2b_cond.v
module lut_multiplier_2b_cond
(
    input resetn_2b,
    input clk_2b,
    input[31:0] source_number_2b_0,
    input[1:0] source_number_2b_1,

    output reg[63:0] result_2b
);

always@(posedge clk_2b) begin
    if(resetn_2b == 1) begin
        result_2b <= 0;
    end
    else begin
        if(source_number_2b_1 == 0) begin
            result_2b <= 0;
        end
        else if (source_number_2b_1 == 1) begin
            result_2b <= source_number_2b_0;
        end
        else if (source_number_2b_1 == 2) begin
            result_2b <= source_number_2b_0 << 1;           //Desplazamiento metiendo cero.
        end
        else if (source_number_2b_1 == 3) begin
            result_2b <= (source_number_2b_0 << 1) + source_number_2b_0;     //Desplazamiento metiendo cero.
        end
        else begin
            result_2b <= 0;
        end
    end
end

endmodule

lut_32b_multiplier/lut_multiplier_4b_cond.v
`include "lut_multiplier_2b_cond.v"

module lut_multiplier_4b_cond
(
    input resetn_4b,
    input clk_4b,
    input[31:0] source_number_4b_0,
    input[3:0] source_number_4b_1,

    output reg[63:0] result_4b
);

wire[31:0] result_4b_0, result_4b_1;

always @ (*) begin
    if(resetn_4b == 1) begin
        result_4b = 0;
    end
    else begin
        result_4b = result_4b_0 + 4*result_4b_1;
    end
end

//lut_multiplier_2b instances.

lut_multiplier_2b_cond lut_2B_0(
    .resetn_2b              (resetn_4b),
    .clk_2b                 (clk_4b),
    .source_number_2b_0     (source_number_4b_0),
    .source_number_2b_1     (source_number_4b_1[1:0]),
    .result_2b              (result_4b_0)
);

lut_multiplier_2b_cond lut_2B_1(
    .resetn_2b              (resetn_4b),
    .clk_2b                 (clk_4b),
    .source_number_2b_0     (source_number_4b_0),
    .source_number_2b_1     (source_number_4b_1[3:2]),
    .result_2b              (result_4b_1)
);

endmodule

lut_32b_multiplier/lut_multiplier_32b_cond.v
`include "lut_multiplier_4b_cond.v"

module lut_multiplier_32b_cond
(
    input resetn_32b,
    input clk_32b,
    input[31:0] source_number_32b_0,
    input[31:0] source_number_32b_1,

    output reg[63:0] result_64b
);

wire[63:0] result_64b_0, result_64b_1, result_64b_2, result_64b_3, result_64b_4, result_64b_5, result_64b_6, result_64b_7;

always @ (*) begin
    if(resetn_32b == 1) begin
        result_64b = 0;
    end
    else begin
        result_64b = result_64b_0 + (result_64b_1<<4)
                                  + (result_64b_2<<8)
                                  + (result_64b_3<<12)
                                  + (result_64b_4<<16)
                                  + (result_64b_5<<20)
                                  + (result_64b_6<<24)
                                  + (result_64b_7<<28);
    end
end

//lut_4b_multiplier instances.

lut_multiplier_4b_cond lut_4B_0(
    .resetn_4b              (resetn_32b),
    .clk_4b                 (clk_32b),
    .source_number_4b_0     (source_number_32b_0),
    .source_number_4b_1     (source_number_32b_1[3:0]),
    .result_4b              (result_64b_0)
);

lut_multiplier_4b_cond lut_4B_1(
    .resetn_4b              (resetn_32b),
    .clk_4b                 (clk_32b),
    .source_number_4b_0     (source_number_32b_0),
    .source_number_4b_1     (source_number_32b_1[7:4]),
    .result_4b              (result_64b_1)
);

lut_multiplier_4b_cond lut_4B_2(
    .resetn_4b              (resetn_32b),
    .clk_4b                 (clk_32b),
    .source_number_4b_0     (source_number_32b_0),
    .source_number_4b_1     (source_number_32b_1[11:8]),
    .result_4b              (result_64b_2)
);

lut_multiplier_4b_cond lut_4B_3(
    .resetn_4b              (resetn_32b),
    .clk_4b                 (clk_32b),
    .source_number_4b_0     (source_number_32b_0),
    .source_number_4b_1     (source_number_32b_1[15:12]),
    .result_4b              (result_64b_3)
);

lut_multiplier_4b_cond lut_4B_4(
    .resetn_4b              (resetn_32b),
    .clk_4b                 (clk_32b),
    .source_number_4b_0     (source_number_32b_0),
    .source_number_4b_1     (source_number_32b_1[19:16]),
    .result_4b              (result_64b_4)
);

lut_multiplier_4b_cond lut_4B_5(
    .resetn_4b              (resetn_32b),
    .clk_4b                 (clk_32b),
    .source_number_4b_0     (source_number_32b_0),
    .source_number_4b_1     (source_number_32b_1[23:20]),
    .result_4b              (result_64b_5)
);

lut_multiplier_4b_cond lut_4B_6(
    .resetn_4b              (resetn_32b),
    .clk_4b                 (clk_32b),
    .source_number_4b_0     (source_number_32b_0),
    .source_number_4b_1     (source_number_32b_1[27:24]),
    .result_4b              (result_64b_6)
);

lut_multiplier_4b_cond lut_4B_7(
    .resetn_4b              (resetn_32b),
    .clk_4b                 (clk_32b),
    .source_number_4b_0     (source_number_32b_0),
    .source_number_4b_1     (source_number_32b_1[31:28]),
    .result_4b              (result_64b_7)
);

endmodule

lut_32b_multiplier/test_bench.v
`timescale 1ns/100ps

`include "lut_multiplier_32b_cond.v"
`include "test.v"

module test_bench;

wire resetn_32b, clk_32b;
wire[31:0] source_number_32b_0, source_number_32b_1;
wire[63:0] result_64b; 

lut_multiplier_32b_cond COND(
    /*AUTOINST*/
			     // Outputs
			     .result_64b	(result_64b[63:0]),
			     // Inputs
			     .resetn_32b	(resetn_32b),
			     .clk_32b		(clk_32b),
			     .source_number_32b_0(source_number_32b_0[31:0]),
			     .source_number_32b_1(source_number_32b_1[31:0]));

test TEST(
    /*AUTOINST*/
	  // Outputs
	  .resetn_32b			(resetn_32b),
	  .clk_32b			(clk_32b),
	  .source_number_32b_0		(source_number_32b_0[31:0]),
	  .source_number_32b_1		(source_number_32b_1[31:0]),
	  // Inputs
	  .result_64b			(result_64b[63:0]));
endmodule

lut_32b_multiplier/lut_multiplier_32b.vcd
$date
	Thu May 13 18:41:48 2021
$end
$version
	Icarus Verilog
$end
$timescale
	100ps
$end
$scope module test_bench $end
$var wire 32 ! source_number_32b_1 [31:0] $end
$var wire 32 " source_number_32b_0 [31:0] $end
$var wire 64 # result_64b [63:0] $end
$var wire 1 $ resetn_32b $end
$var wire 1 % clk_32b $end
$scope module COND $end
$var wire 32 & source_number_32b_1 [31:0] $end
$var wire 32 ' source_number_32b_0 [31:0] $end
$var wire 64 ( result_64b_7 [63:0] $end
$var wire 64 ) result_64b_6 [63:0] $end
$var wire 64 * result_64b_5 [63:0] $end
$var wire 64 + result_64b_4 [63:0] $end
$var wire 64 , result_64b_3 [63:0] $end
$var wire 64 - result_64b_2 [63:0] $end
$var wire 64 . result_64b_1 [63:0] $end
$var wire 64 / result_64b_0 [63:0] $end
$var wire 1 $ resetn_32b $end
$var wire 1 % clk_32b $end
$var reg 64 0 result_64b [63:0] $end
$scope module lut_4B_0 $end
$var wire 4 1 source_number_4b_1 [3:0] $end
$var wire 32 2 source_number_4b_0 [31:0] $end
$var wire 32 3 result_4b_1 [31:0] $end
$var wire 32 4 result_4b_0 [31:0] $end
$var wire 1 $ resetn_4b $end
$var wire 1 % clk_4b $end
$var reg 64 5 result_4b [63:0] $end
$scope module lut_2B_0 $end
$var wire 2 6 source_number_2b_1 [1:0] $end
$var wire 32 7 source_number_2b_0 [31:0] $end
$var wire 1 $ resetn_2b $end
$var wire 1 % clk_2b $end
$var reg 64 8 result_2b [63:0] $end
$upscope $end
$scope module lut_2B_1 $end
$var wire 2 9 source_number_2b_1 [1:0] $end
$var wire 32 : source_number_2b_0 [31:0] $end
$var wire 1 $ resetn_2b $end
$var wire 1 % clk_2b $end
$var reg 64 ; result_2b [63:0] $end
$upscope $end
$upscope $end
$scope module lut_4B_1 $end
$var wire 4 < source_number_4b_1 [3:0] $end
$var wire 32 = source_number_4b_0 [31:0] $end
$var wire 32 > result_4b_1 [31:0] $end
$var wire 32 ? result_4b_0 [31:0] $end
$var wire 1 $ resetn_4b $end
$var wire 1 % clk_4b $end
$var reg 64 @ result_4b [63:0] $end
$scope module lut_2B_0 $end
$var wire 2 A source_number_2b_1 [1:0] $end
$var wire 32 B source_number_2b_0 [31:0] $end
$var wire 1 $ resetn_2b $end
$var wire 1 % clk_2b $end
$var reg 64 C result_2b [63:0] $end
$upscope $end
$scope module lut_2B_1 $end
$var wire 2 D source_number_2b_1 [1:0] $end
$var wire 32 E source_number_2b_0 [31:0] $end
$var wire 1 $ resetn_2b $end
$var wire 1 % clk_2b $end
$var reg 64 F result_2b [63:0] $end
$upscope $end
$upscope $end
$scope module lut_4B_2 $end
$var wire 4 G source_number_4b_1 [3:0] $end
$var wire 32 H source_number_4b_0 [31:0] $end
$var wire 32 I result_4b_1 [31:0] $end
$var wire 32 J result_4b_0 [31:0] $end
$var wire 1 $ resetn_4b $end
$var wire 1 % clk_4b $end
$var reg 64 K result_4b [63:0] $end
$scope module lut_2B_0 $end
$var wire 2 L source_number_2b_1 [1:0] $end
$var wire 32 M source_number_2b_0 [31:0] $end
$var wire 1 $ resetn_2b $end
$var wire 1 % clk_2b $end
$var reg 64 N result_2b [63:0] $end
$upscope $end
$scope module lut_2B_1 $end
$var wire 2 O source_number_2b_1 [1:0] $end
$var wire 32 P source_number_2b_0 [31:0] $end
$var wire 1 $ resetn_2b $end
$var wire 1 % clk_2b $end
$var reg 64 Q result_2b [63:0] $end
$upscope $end
$upscope $end
$scope module lut_4B_3 $end
$var wire 4 R source_number_4b_1 [3:0] $end
$var wire 32 S source_number_4b_0 [31:0] $end
$var wire 32 T result_4b_1 [31:0] $end
$var wire 32 U result_4b_0 [31:0] $end
$var wire 1 $ resetn_4b $end
$var wire 1 % clk_4b $end
$var reg 64 V result_4b [63:0] $end
$scope module lut_2B_0 $end
$var wire 2 W source_number_2b_1 [1:0] $end
$var wire 32 X source_number_2b_0 [31:0] $end
$var wire 1 $ resetn_2b $end
$var wire 1 % clk_2b $end
$var reg 64 Y result_2b [63:0] $end
$upscope $end
$scope module lut_2B_1 $end
$var wire 2 Z source_number_2b_1 [1:0] $end
$var wire 32 [ source_number_2b_0 [31:0] $end
$var wire 1 $ resetn_2b $end
$var wire 1 % clk_2b $end
$var reg 64 \ result_2b [63:0] $end
$upscope $end
$upscope $end
$scope module lut_4B_4 $end
$var wire 4 ] source_number_4b_1 [3:0] $end
$var wire 32 ^ source_number_4b_0 [31:0] $end
$var wire 32 _ result_4b_1 [31:0] $end
$var wire 32 ` result_4b_0 [31:0] $end
$var wire 1 $ resetn_4b $end
$var wire 1 % clk_4b $end
$var reg 64 a result_4b [63:0] $end
$scope module lut_2B_0 $end
$var wire 2 b source_number_2b_1 [1:0] $end
$var wire 32 c source_number_2b_0 [31:0] $end
$var wire 1 $ resetn_2b $end
$var wire 1 % clk_2b $end
$var reg 64 d result_2b [63:0] $end
$upscope $end
$scope module lut_2B_1 $end
$var wire 2 e source_number_2b_1 [1:0] $end
$var wire 32 f source_number_2b_0 [31:0] $end
$var wire 1 $ resetn_2b $end
$var wire 1 % clk_2b $end
$var reg 64 g result_2b [63:0] $end
$upscope $end
$upscope $end
$scope module lut_4B_5 $end
$var wire 4 h source_number_4b_1 [3:0] $end
$var wire 32 i source_number_4b_0 [31:0] $end
$var wire 32 j result_4b_1 [31:0] $end
$var wire 32 k result_4b_0 [31:0] $end
$var wire 1 $ resetn_4b $end
$var wire 1 % clk_4b $end
$var reg 64 l result_4b [63:0] $end
$scope module lut_2B_0 $end
$var wire 2 m source_number_2b_1 [1:0] $end
$var wire 32 n source_number_2b_0 [31:0] $end
$var wire 1 $ resetn_2b $end
$var wire 1 % clk_2b $end
$var reg 64 o result_2b [63:0] $end
$upscope $end
$scope module lut_2B_1 $end
$var wire 2 p source_number_2b_1 [1:0] $end
$var wire 32 q source_number_2b_0 [31:0] $end
$var wire 1 $ resetn_2b $end
$var wire 1 % clk_2b $end
$var reg 64 r result_2b [63:0] $end
$upscope $end
$upscope $end
$scope module lut_4B_6 $end
$var wire 4 s source_number_4b_1 [3:0] $end
$var wire 32 t source_number_4b_0 [31:0] $end
$var wire 32 u result_4b_1 [31:0] $end
$var wire 32 v result_4b_0 [31:0] $end
$var wire 1 $ resetn_4b $end
$var wire 1 % clk_4b $end
$var reg 64 w result_4b [63:0] $end
$scope module lut_2B_0 $end
$var wire 2 x source_number_2b_1 [1:0] $end
$var wire 32 y source_number_2b_0 [31:0] $end
$var wire 1 $ resetn_2b $end
$var wire 1 % clk_2b $end
$var reg 64 z result_2b [63:0] $end
$upscope $end
$scope module lut_2B_1 $end
$var wire 2 { source_number_2b_1 [1:0] $end
$var wire 32 | source_number_2b_0 [31:0] $end
$var wire 1 $ resetn_2b $end
$var wire 1 % clk_2b $end
$var reg 64 } result_2b [63:0] $end
$upscope $end
$upscope $end
$scope module lut_4B_7 $end
$var wire 4 ~ source_number_4b_1 [3:0] $end
$var wire 32 !" source_number_4b_0 [31:0] $end
$var wire 32 "" result_4b_1 [31:0] $end
$var wire 32 #" result_4b_0 [31:0] $end
$var wire 1 $ resetn_4b $end
$var wire 1 % clk_4b $end
$var reg 64 $" result_4b [63:0] $end
$scope module lut_2B_0 $end
$var wire 2 %" source_number_2b_1 [1:0] $end
$var wire 32 &" source_number_2b_0 [31:0] $end
$var wire 1 $ resetn_2b $end
$var wire 1 % clk_2b $end
$var reg 64 '" result_2b [63:0] $end
$upscope $end
$scope module lut_2B_1 $end
$var wire 2 (" source_number_2b_1 [1:0] $end
$var wire 32 )" source_number_2b_0 [31:0] $end
$var wire 1 $ resetn_2b $end
$var wire 1 % clk_2b $end
$var reg 64 *" result_2b [63:0] $end
$upscope $end
$upscope $end
$upscope $end
$scope module TEST $end
$var wire 64 +" result_64b [63:0] $end
$var reg 1 % clk_32b $end
$var reg 1 $ resetn_32b $end
$var reg 32 ," source_number_32b_0 [31:0] $end
$var reg 32 -" source_number_32b_1 [31:0] $end
$upscope $end
$upscope $end
$enddefinitions $end
#0
$dumpvars
bx -"
bx ,"
b0 +"
bx *"
bx )"
bx ("
bx '"
bx &"
bx %"
b0 $"
bx #"
bx ""
bx !"
bx ~
bx }
bx |
bx {
bx z
bx y
bx x
b0 w
bx v
bx u
bx t
bx s
bx r
bx q
bx p
bx o
bx n
bx m
b0 l
bx k
bx j
bx i
bx h
bx g
bx f
bx e
bx d
bx c
bx b
b0 a
bx `
bx _
bx ^
bx ]
bx \
bx [
bx Z
bx Y
bx X
bx W
b0 V
bx U
bx T
bx S
bx R
bx Q
bx P
bx O
bx N
bx M
bx L
b0 K
bx J
bx I
bx H
bx G
bx F
bx E
bx D
bx C
bx B
bx A
b0 @
bx ?
bx >
bx =
bx <
bx ;
bx :
bx 9
bx 8
bx 7
bx 6
b0 5
bx 4
bx 3
bx 2
bx 1
b0 0
b0 /
b0 .
b0 -
b0 ,
b0 +
b0 *
b0 )
b0 (
bx '
bx &
0%
1$
b0 #
bx "
bx !
$end
#20
b0 4
b0 3
b0 ?
b0 >
b0 J
b0 I
b0 U
b0 T
b0 `
b0 _
b0 k
b0 j
b0 v
b0 u
b0 #"
b0 ""
b0 8
b0 ;
b0 C
b0 F
b0 N
b0 Q
b0 Y
b0 \
b0 d
b0 g
b0 o
b0 r
b0 z
b0 }
b0 '"
b0 *"
1%
#40
0%
#60
0$
1%
#80
0%
#100
b0 %"
b0 ("
b0 x
b0 {
b0 m
b0 p
b0 b
b0 e
b0 W
b0 Z
b0 L
b0 O
b0 A
b0 D
b10 6
b0 9
b0 ~
b0 s
b0 h
b0 ]
b0 R
b0 G
b0 <
b10 1
b10 !
b10 &
b10 -"
b1111000 "
b1111000 '
b1111000 2
b1111000 7
b1111000 :
b1111000 =
b1111000 B
b1111000 E
b1111000 H
b1111000 M
b1111000 P
b1111000 S
b1111000 X
b1111000 [
b1111000 ^
b1111000 c
b1111000 f
b1111000 i
b1111000 n
b1111000 q
b1111000 t
b1111000 y
b1111000 |
b1111000 !"
b1111000 &"
b1111000 )"
b1111000 ,"
1%
#120
0%
#140
b11110000 #
b11110000 0
b11110000 +"
b11110000 /
b11110000 5
b11110000 4
b11110000 8
1%
#160
0%
#180
b1 A
b1 6
b1 <
b1 1
b10001 !
b10001 &
b10001 -"
b10011 "
b10011 '
b10011 2
b10011 7
b10011 :
b10011 =
b10011 B
b10011 E
b10011 H
b10011 M
b10011 P
b10011 S
b10011 X
b10011 [
b10011 ^
b10011 c
b10011 f
b10011 i
b10011 n
b10011 q
b10011 t
b10011 y
b10011 |
b10011 !"
b10011 &"
b10011 )"
b10011 ,"
1%
#200
0%
#220
b101000011 #
b101000011 0
b101000011 +"
b10011 .
b10011 @
b10011 /
b10011 5
b10011 ?
b10011 4
b10011 C
b10011 8
1%
#240
0%
#260
b0 A
b11 6
b10 9
b0 <
b1011 1
b1011 !
b1011 &
b1011 -"
b1101110101111100000000 "
b1101110101111100000000 '
b1101110101111100000000 2
b1101110101111100000000 7
b1101110101111100000000 :
b1101110101111100000000 =
b1101110101111100000000 B
b1101110101111100000000 E
b1101110101111100000000 H
b1101110101111100000000 M
b1101110101111100000000 P
b1101110101111100000000 S
b1101110101111100000000 X
b1101110101111100000000 [
b1101110101111100000000 ^
b1101110101111100000000 c
b1101110101111100000000 f
b1101110101111100000000 i
b1101110101111100000000 n
b1101110101111100000000 q
b1101110101111100000000 t
b1101110101111100000000 y
b1101110101111100000000 |
b1101110101111100000000 !"
b1101110101111100000000 &"
b1101110101111100000000 )"
b1101110101111100000000 ,"
1%
#280
0%
#300
b10011000010001010100000000 #
b10011000010001010100000000 0
b10011000010001010100000000 +"
b0 .
b0 @
b10011000010001010100000000 /
b10011000010001010100000000 5
b0 ?
b11011101011111000000000 3
b101001100001110100000000 4
b0 C
b11011101011111000000000 ;
b101001100001110100000000 8
1%
#320
0%
#340
b0 6
b11 9
b1100 1
b1100 !
b1100 &
b1100 -"
b10011000010001010100000000 "
b10011000010001010100000000 '
b10011000010001010100000000 2
b10011000010001010100000000 7
b10011000010001010100000000 :
b10011000010001010100000000 =
b10011000010001010100000000 B
b10011000010001010100000000 E
b10011000010001010100000000 H
b10011000010001010100000000 M
b10011000010001010100000000 P
b10011000010001010100000000 S
b10011000010001010100000000 X
b10011000010001010100000000 [
b10011000010001010100000000 ^
b10011000010001010100000000 c
b10011000010001010100000000 f
b10011000010001010100000000 i
b10011000010001010100000000 n
b10011000010001010100000000 q
b10011000010001010100000000 t
b10011000010001010100000000 y
b10011000010001010100000000 |
b10011000010001010100000000 !"
b10011000010001010100000000 &"
b10011000010001010100000000 )"
b10011000010001010100000000 ,"
1%
#360
0%
#380
b11100100011001111110000000000 #
b11100100011001111110000000000 0
b11100100011001111110000000000 +"
b11100100011001111110000000000 /
b11100100011001111110000000000 5
b111001000110011111100000000 3
b0 4
b111001000110011111100000000 ;
b0 8
1%
#400
0%
#420
b11 m
b11 b
b1 e
b1 W
b1 Z
b11 L
b11 O
b0 9
b11 h
b111 ]
b101 R
b1111 G
b0 1
b1101110101111100000000 !
b1101110101111100000000 &
b1101110101111100000000 -"
1%
#440
0%
#460
b100000111011110110001001110010110000000000000000 #
b100000111011110110001001110010110000000000000000 0
b100000111011110110001001110010110000000000000000 +"
b111001000110011111100000000 *
b111001000110011111100000000 l
b10000101001111001001100000000 +
b10000101001111001001100000000 a
b1011111001010110100100000000 ,
b1011111001010110100100000000 V
b100011101100000011101100000000 -
b100011101100000011101100000000 K
b0 /
b0 5
b111001000110011111100000000 k
b10011000010001010100000000 _
b111001000110011111100000000 `
b10011000010001010100000000 T
b10011000010001010100000000 U
b111001000110011111100000000 I
b111001000110011111100000000 J
b0 3
b111001000110011111100000000 o
b10011000010001010100000000 g
b111001000110011111100000000 d
b10011000010001010100000000 \
b10011000010001010100000000 Y
b111001000110011111100000000 Q
b111001000110011111100000000 N
b0 ;
1%
