lut_32b_multiplier/test.v
module test
(
    output reg resetn_32b,
    output reg clk_32b,
    output reg[31:0] source_number_32b_0,
    output reg[31:0] source_number_32b_1,

    input[63:0] result_64b
); 

initial begin
    $dumpfile("lut_multiplier_32b.vcd");
	$dumpvars;

    @(posedge clk_32b);
	@(posedge clk_32b);
    @(posedge clk_32b);
        source_number_32b_0 <= 120;
        source_number_32b_1 <= 2;
    repeat(2) @(posedge clk_32b);
        source_number_32b_0 <= 19;
        source_number_32b_1 <= 17;
    repeat(2) @(posedge clk_32b);
        source_number_32b_0 <= 3628800;
        source_number_32b_1 <= 11;
    repeat(2) @(posedge clk_32b);
        source_number_32b_0 <= 39916800;
        source_number_32b_1 <= 12;
    repeat(2) @(posedge clk_32b);
        source_number_32b_0 <= 39916800;
        source_number_32b_1 <= 3628800;
    repeat(27) @(posedge clk_32b);
        source_number_32b_0 <= 39916800;

    $finish;
end

//clk_32b.
initial clk_32b <= 0;
always	#2 clk_32b <= ~clk_32b;

//resetn.
initial
begin
	#0
	resetn_32b = 1'b1;
	@(posedge clk_32b);
	resetn_32b = 1'b1;
	@(posedge clk_32b);
	resetn_32b = 1'b0;
end

endmodule

lut_4b_multiplier/lut_multiplier_2b_cond.v
module lut_multiplier_2b_cond
(
    input resetn_2b,
    input clk_2b,
    input[31:0] source_number_2b_0,
    input[1:0] source_number_2b_1,

    output reg[63:0] result_2b
);

always@(posedge clk_2b) begin
    if(resetn_2b == 1) begin
        result_2b <= 0;
    end
    else begin
        if(source_number_2b_1 == 0) begin
            result_2b <= 0;
        end
        else if (source_number_2b_1 == 1) begin
            result_2b <= source_number_2b_0;
        end
        else if (source_number_2b_1 == 2) begin
            result_2b <= source_number_2b_0 << 1;           //Desplazamiento metiendo cero.
        end
        else if (source_number_2b_1 == 3) begin
            result_2b <= (source_number_2b_0 << 1) + source_number_2b_0;     //Desplazamiento metiendo cero.
        end
        else begin
            result_2b <= 0;
        end
    end
end

endmodule

lut_32b_multiplier/lut_multiplier_4b_cond.v
`include "lut_multiplier_2b_cond.v"

module lut_multiplier_4b_cond
(
    input resetn_4b,
    input clk_4b,
    input[31:0] source_number_4b_0,
    input[3:0] source_number_4b_1,

    output reg[63:0] result_4b
);

wire[31:0] result_4b_0, result_4b_1;

always @ (*) begin
    if(resetn_4b == 1) begin
        result_4b = 0;
    end
    else begin
        result_4b = result_4b_0 + 4*result_4b_1;
    end
end

//lut_multiplier_2b instances.

lut_multiplier_2b_cond lut_2B_0(
    .resetn_2b              (resetn_4b),
    .clk_2b                 (clk_4b),
    .source_number_2b_0     (source_number_4b_0),
    .source_number_2b_1     (source_number_4b_1[1:0]),
    .result_2b              (result_4b_0)
);

lut_multiplier_2b_cond lut_2B_1(
    .resetn_2b              (resetn_4b),
    .clk_2b                 (clk_4b),
    .source_number_2b_0     (source_number_4b_0),
    .source_number_2b_1     (source_number_4b_1[3:2]),
    .result_2b              (result_4b_1)
);

endmodule

lut_32b_multiplier/lut_multiplier_32b_cond.v
`include "lut_multiplier_4b_cond.v"

module lut_multiplier_32b_cond
(
    input resetn_32b,
    input clk_32b,
    input[31:0] source_number_32b_0,
    input[31:0] source_number_32b_1,

    output reg[63:0] result_64b
);

wire[63:0] result_64b_0, result_64b_1, result_64b_2, result_64b_3, result_64b_4, result_64b_5, result_64b_6, result_64b_7;

always @ (*) begin
    if(resetn_32b == 1) begin
        result_64b = 0;
    end
    else begin
        result_64b = result_64b_0 + (result_64b_1<<4)
                                  + (result_64b_2<<8)
                                  + (result_64b_3<<12)
                                  + (result_64b_4<<16)
                                  + (result_64b_5<<20)
                                  + (result_64b_6<<24)
                                  + (result_64b_7<<28);
    end
end

//lut_4b_multiplier instances.

lut_multiplier_4b_cond lut_4B_0(
    .resetn_4b              (resetn_32b),
    .clk_4b                 (clk_32b),
    .source_number_4b_0     (source_number_32b_0),
    .source_number_4b_1     (source_number_32b_1[3:0]),
    .result_4b              (result_64b_0)
);

lut_multiplier_4b_cond lut_4B_1(
    .resetn_4b              (resetn_32b),
    .clk_4b                 (clk_32b),
    .source_number_4b_0     (source_number_32b_0),
    .source_number_4b_1     (source_number_32b_1[7:4]),
    .result_4b              (result_64b_1)
);

lut_multiplier_4b_cond lut_4B_2(
    .resetn_4b              (resetn_32b),
    .clk_4b                 (clk_32b),
    .source_number_4b_0     (source_number_32b_0),
    .source_number_4b_1     (source_number_32b_1[11:8]),
    .result_4b              (result_64b_2)
);

lut_multiplier_4b_cond lut_4B_3(
    .resetn_4b              (resetn_32b),
    .clk_4b                 (clk_32b),
    .source_number_4b_0     (source_number_32b_0),
    .source_number_4b_1     (source_number_32b_1[15:12]),
    .result_4b              (result_64b_3)
);

lut_multiplier_4b_cond lut_4B_4(
    .resetn_4b              (resetn_32b),
    .clk_4b                 (clk_32b),
    .source_number_4b_0     (source_number_32b_0),
    .source_number_4b_1     (source_number_32b_1[19:16]),
    .result_4b              (result_64b_4)
);

lut_multiplier_4b_cond lut_4B_5(
    .resetn_4b              (resetn_32b),
    .clk_4b                 (clk_32b),
    .source_number_4b_0     (source_number_32b_0),
    .source_number_4b_1     (source_number_32b_1[23:20]),
    .result_4b              (result_64b_5)
);

lut_multiplier_4b_cond lut_4B_6(
    .resetn_4b              (resetn_32b),
    .clk_4b                 (clk_32b),
    .source_number_4b_0     (source_number_32b_0),
    .source_number_4b_1     (source_number_32b_1[27:24]),
    .result_4b              (result_64b_6)
);

lut_multiplier_4b_cond lut_4B_7(
    .resetn_4b              (resetn_32b),
    .clk_4b                 (clk_32b),
    .source_number_4b_0     (source_number_32b_0),
    .source_number_4b_1     (source_number_32b_1[31:28]),
    .result_4b              (result_64b_7)
);

endmodule

lut_32b_multiplier/test_bench.v
`timescale 1ns/100ps

`include "lut_multiplier_32b_cond.v"
`include "test.v"

module test_bench;

wire resetn_32b, clk_32b;
wire[31:0] source_number_32b_0, source_number_32b_1;
wire[63:0] result_64b; 

lut_multiplier_32b_cond COND(
    /*AUTOINST*/
			     // Outputs
			     .result_64b	(result_64b[63:0]),
			     // Inputs
			     .resetn_32b	(resetn_32b),
			     .clk_32b		(clk_32b),
			     .source_number_32b_0(source_number_32b_0[31:0]),
			     .source_number_32b_1(source_number_32b_1[31:0]));

test TEST(
    /*AUTOINST*/
	  // Outputs
	  .resetn_32b			(resetn_32b),
	  .clk_32b			(clk_32b),
	  .source_number_32b_0		(source_number_32b_0[31:0]),
	  .source_number_32b_1		(source_number_32b_1[31:0]),
	  // Inputs
	  .result_64b			(result_64b[63:0]));
endmodule

lut_32b_multiplier/lut_multiplier_4b.vcd
$date
	Mon May  3 00:04:13 2021
$end
$version
	Icarus Verilog
$end
$timescale
	100ps
$end
$scope module test_bench $end
$scope module COND $end
$var wire 1 ! clk_32b $end
$var wire 1 " resetn_32b $end
$var wire 32 # source_number_32b_0 [31:0] $end
$var wire 32 $ source_number_32b_1 [31:0] $end
$var wire 64 % result_64b_7 [63:0] $end
$var wire 64 & result_64b_6 [63:0] $end
$var wire 64 ' result_64b_5 [63:0] $end
$var wire 64 ( result_64b_4 [63:0] $end
$var wire 64 ) result_64b_3 [63:0] $end
$var wire 64 * result_64b_2 [63:0] $end
$var wire 64 + result_64b_1 [63:0] $end
$var wire 64 , result_64b_0 [63:0] $end
$var reg 64 - result_64b [63:0] $end
$scope module lut_4B_0 $end
$var wire 1 ! clk_4b $end
$var wire 1 " resetn_4b $end
$var wire 32 . source_number_4b_0 [31:0] $end
$var wire 4 / source_number_4b_1 [3:0] $end
$var wire 32 0 result_4b_1 [31:0] $end
$var wire 32 1 result_4b_0 [31:0] $end
$var reg 64 2 result_4b [63:0] $end
$scope module lut_2B_0 $end
$var wire 1 ! clk_2b $end
$var wire 1 " resetn_2b $end
$var wire 32 3 source_number_2b_0 [31:0] $end
$var wire 2 4 source_number_2b_1 [1:0] $end
$var reg 64 5 result_2b [63:0] $end
$upscope $end
$scope module lut_2B_1 $end
$var wire 1 ! clk_2b $end
$var wire 1 " resetn_2b $end
$var wire 32 6 source_number_2b_0 [31:0] $end
$var wire 2 7 source_number_2b_1 [1:0] $end
$var reg 64 8 result_2b [63:0] $end
$upscope $end
$upscope $end
$scope module lut_4B_1 $end
$var wire 1 ! clk_4b $end
$var wire 1 " resetn_4b $end
$var wire 32 9 source_number_4b_0 [31:0] $end
$var wire 4 : source_number_4b_1 [3:0] $end
$var wire 32 ; result_4b_1 [31:0] $end
$var wire 32 < result_4b_0 [31:0] $end
$var reg 64 = result_4b [63:0] $end
$scope module lut_2B_0 $end
$var wire 1 ! clk_2b $end
$var wire 1 " resetn_2b $end
$var wire 32 > source_number_2b_0 [31:0] $end
$var wire 2 ? source_number_2b_1 [1:0] $end
$var reg 64 @ result_2b [63:0] $end
$upscope $end
$scope module lut_2B_1 $end
$var wire 1 ! clk_2b $end
$var wire 1 " resetn_2b $end
$var wire 32 A source_number_2b_0 [31:0] $end
$var wire 2 B source_number_2b_1 [1:0] $end
$var reg 64 C result_2b [63:0] $end
$upscope $end
$upscope $end
$scope module lut_4B_2 $end
$var wire 1 ! clk_4b $end
$var wire 1 " resetn_4b $end
$var wire 32 D source_number_4b_0 [31:0] $end
$var wire 4 E source_number_4b_1 [3:0] $end
$var wire 32 F result_4b_1 [31:0] $end
$var wire 32 G result_4b_0 [31:0] $end
$var reg 64 H result_4b [63:0] $end
$scope module lut_2B_0 $end
$var wire 1 ! clk_2b $end
$var wire 1 " resetn_2b $end
$var wire 32 I source_number_2b_0 [31:0] $end
$var wire 2 J source_number_2b_1 [1:0] $end
$var reg 64 K result_2b [63:0] $end
$upscope $end
$scope module lut_2B_1 $end
$var wire 1 ! clk_2b $end
$var wire 1 " resetn_2b $end
$var wire 32 L source_number_2b_0 [31:0] $end
$var wire 2 M source_number_2b_1 [1:0] $end
$var reg 64 N result_2b [63:0] $end
$upscope $end
$upscope $end
$scope module lut_4B_3 $end
$var wire 1 ! clk_4b $end
$var wire 1 " resetn_4b $end
$var wire 32 O source_number_4b_0 [31:0] $end
$var wire 4 P source_number_4b_1 [3:0] $end
$var wire 32 Q result_4b_1 [31:0] $end
$var wire 32 R result_4b_0 [31:0] $end
$var reg 64 S result_4b [63:0] $end
$scope module lut_2B_0 $end
$var wire 1 ! clk_2b $end
$var wire 1 " resetn_2b $end
$var wire 32 T source_number_2b_0 [31:0] $end
$var wire 2 U source_number_2b_1 [1:0] $end
$var reg 64 V result_2b [63:0] $end
$upscope $end
$scope module lut_2B_1 $end
$var wire 1 ! clk_2b $end
$var wire 1 " resetn_2b $end
$var wire 32 W source_number_2b_0 [31:0] $end
$var wire 2 X source_number_2b_1 [1:0] $end
$var reg 64 Y result_2b [63:0] $end
$upscope $end
$upscope $end
$scope module lut_4B_4 $end
$var wire 1 ! clk_4b $end
$var wire 1 " resetn_4b $end
$var wire 32 Z source_number_4b_0 [31:0] $end
$var wire 4 [ source_number_4b_1 [3:0] $end
$var wire 32 \ result_4b_1 [31:0] $end
$var wire 32 ] result_4b_0 [31:0] $end
$var reg 64 ^ result_4b [63:0] $end
$scope module lut_2B_0 $end
$var wire 1 ! clk_2b $end
$var wire 1 " resetn_2b $end
$var wire 32 _ source_number_2b_0 [31:0] $end
$var wire 2 ` source_number_2b_1 [1:0] $end
$var reg 64 a result_2b [63:0] $end
$upscope $end
$scope module lut_2B_1 $end
$var wire 1 ! clk_2b $end
$var wire 1 " resetn_2b $end
$var wire 32 b source_number_2b_0 [31:0] $end
$var wire 2 c source_number_2b_1 [1:0] $end
$var reg 64 d result_2b [63:0] $end
$upscope $end
$upscope $end
$scope module lut_4B_5 $end
$var wire 1 ! clk_4b $end
$var wire 1 " resetn_4b $end
$var wire 32 e source_number_4b_0 [31:0] $end
$var wire 4 f source_number_4b_1 [3:0] $end
$var wire 32 g result_4b_1 [31:0] $end
$var wire 32 h result_4b_0 [31:0] $end
$var reg 64 i result_4b [63:0] $end
$scope module lut_2B_0 $end
$var wire 1 ! clk_2b $end
$var wire 1 " resetn_2b $end
$var wire 32 j source_number_2b_0 [31:0] $end
$var wire 2 k source_number_2b_1 [1:0] $end
$var reg 64 l result_2b [63:0] $end
$upscope $end
$scope module lut_2B_1 $end
$var wire 1 ! clk_2b $end
$var wire 1 " resetn_2b $end
$var wire 32 m source_number_2b_0 [31:0] $end
$var wire 2 n source_number_2b_1 [1:0] $end
$var reg 64 o result_2b [63:0] $end
$upscope $end
$upscope $end
$scope module lut_4B_6 $end
$var wire 1 ! clk_4b $end
$var wire 1 " resetn_4b $end
$var wire 32 p source_number_4b_0 [31:0] $end
$var wire 4 q source_number_4b_1 [3:0] $end
$var wire 32 r result_4b_1 [31:0] $end
$var wire 32 s result_4b_0 [31:0] $end
$var reg 64 t result_4b [63:0] $end
$scope module lut_2B_0 $end
$var wire 1 ! clk_2b $end
$var wire 1 " resetn_2b $end
$var wire 32 u source_number_2b_0 [31:0] $end
$var wire 2 v source_number_2b_1 [1:0] $end
$var reg 64 w result_2b [63:0] $end
$upscope $end
$scope module lut_2B_1 $end
$var wire 1 ! clk_2b $end
$var wire 1 " resetn_2b $end
$var wire 32 x source_number_2b_0 [31:0] $end
$var wire 2 y source_number_2b_1 [1:0] $end
$var reg 64 z result_2b [63:0] $end
$upscope $end
$upscope $end
$scope module lut_4B_7 $end
$var wire 1 ! clk_4b $end
$var wire 1 " resetn_4b $end
$var wire 32 { source_number_4b_0 [31:0] $end
$var wire 4 | source_number_4b_1 [3:0] $end
$var wire 32 } result_4b_1 [31:0] $end
$var wire 32 ~ result_4b_0 [31:0] $end
$var reg 64 !" result_4b [63:0] $end
$scope module lut_2B_0 $end
$var wire 1 ! clk_2b $end
$var wire 1 " resetn_2b $end
$var wire 32 "" source_number_2b_0 [31:0] $end
$var wire 2 #" source_number_2b_1 [1:0] $end
$var reg 64 $" result_2b [63:0] $end
$upscope $end
$scope module lut_2B_1 $end
$var wire 1 ! clk_2b $end
$var wire 1 " resetn_2b $end
$var wire 32 %" source_number_2b_0 [31:0] $end
$var wire 2 &" source_number_2b_1 [1:0] $end
$var reg 64 '" result_2b [63:0] $end
$upscope $end
$upscope $end
$upscope $end
$scope module TEST $end
$var wire 64 (" result_64b [63:0] $end
$var reg 1 )" clk_32b $end
$var reg 1 *" resetn_32b $end
$var reg 32 +" source_number_32b_0 [31:0] $end
$var reg 32 ," source_number_32b_1 [31:0] $end
$upscope $end
$upscope $end
$enddefinitions $end
#0
$dumpvars
bx ,"
bx +"
1*"
0)"
bz ("
bx '"
bz &"
bz %"
bx $"
bz #"
bz ""
bx !"
bx ~
bx }
bz |
bz {
bx z
bz y
bz x
bx w
bz v
bz u
bx t
bx s
bx r
bz q
bz p
bx o
bz n
bz m
bx l
bz k
bz j
bx i
bx h
bx g
bz f
bz e
bx d
bz c
bz b
bx a
bz `
bz _
bx ^
bx ]
bx \
bz [
bz Z
bx Y
bz X
bz W
bx V
bz U
bz T
bx S
bx R
bx Q
bz P
bz O
bx N
bz M
bz L
bx K
bz J
bz I
bx H
bx G
bx F
bz E
bz D
bx C
bz B
bz A
bx @
bz ?
bz >
bx =
bx <
bx ;
bz :
bz 9
bx 8
bz 7
bz 6
bx 5
bz 4
bz 3
bx 2
bx 1
bx 0
bz /
bz .
bx -
bx ,
bx +
bx *
bx )
bx (
bx '
bx &
bx %
bz $
bz #
z"
z!
$end
#20
1)"
#40
0)"
#60
0*"
1)"
#80
0)"
#100
b1001 +"
1)"
#120
0)"
#140
b0 ,"
1)"
#160
0)"
#180
b11 ,"
1)"
#200
0)"
#220
b1000 ,"
1)"
#240
0)"
#260
b10 ,"
1)"
#280
0)"
#300
1)"
#320
0)"
#340
1)"
#360
0)"
#380
1)"
#400
0)"
#420
1)"
#440
0)"
#460
1)"
#480
0)"
#500
b11 ,"
1)"
